setup.py
drf_otp_requests/__init__.py
drf_otp_requests/gae.py
drf_otp_requests.egg-info/PKG-INFO
drf_otp_requests.egg-info/SOURCES.txt
drf_otp_requests.egg-info/dependency_links.txt
drf_otp_requests.egg-info/not-zip-safe
drf_otp_requests.egg-info/requires.txt
drf_otp_requests.egg-info/top_level.txt