Metadata-Version: 1.0
Name: drf-otp-requests
Version: 0.3
Summary: requests for API with OTP permission
Home-page: https://gitlab.com/taelimoh/drf-otp-requests
Author: Tae-lim Oh
Author-email: taelimoh@gmail.com
License: MIT
Keywords: django rest framework drf otp permission requests
Platform: UNKNOWN
